{
    "backend_subscriptionId": "e5e9a94d-5d39-47a4-a878-506a198a389b",
    "backend_rg": "rgp-p-fc1-cloudavcinfra-tfstate",
    "backend_storageaccount": "stapfc1avcinfratfstate",
    "backend_containername" : "packagingvms",
    "credential" : "81b51ae8-6afb-45eb-b2ed-5b626ea69281",    
    "installshieldvmname": "VDE2PIS-",
    "testmachinevmname": "VDE2PTM-",
    "subnet_name": "sub-d-fc1-management-44-111-147-16-28",
    "resource_group_name" : "Packaging-AVC",
    "vnet" : "vnet-d-fc1-avcce2w99-NetworkRG",
    "vnet_rg" : "rg-d-fc1-avcce2w99-NetworkRG-networking",
    "subscriptionId" : "b469b9cd-7522-44f7-b7d7-010f2c9a630f",
    "tenantId": "6e06e42d-6925-47c6-b9e7-9581c7ca302a",  
    "local_techuser" : "",
    "sa_username": "rappsce1repo"

}
